MusicLibrary_bdata
