Metadata-Version: 2.1
Name: MusicLibrary-bdata
Version: 0.9
Summary: Allows users to search for songs and artist or albums and get information about them
Home-page: https://github.com/pauleaguirre/MusicLibrary_bdata
Download-URL: https://github.com/pauleaguirre/MusicLibrary_bdata/archive/refs/tags/v_08.tar.gz
Author: Peio and Paule
Author-email: peio.diaz@alumni.mondragon.edu
License: MIT
Keywords: MUSIC,API,SEARCH
Classifier: Development Status :: 3 - Alpha
Classifier: Intended Audience :: Developers
Classifier: Topic :: Software Development :: Build Tools
Classifier: License :: OSI Approved :: MIT License
Classifier: Programming Language :: Python :: 3.9
Classifier: Programming Language :: Python :: 3.8
License-File: LICENSE.txt
